nova_sdk/__init__.py
nova_sdk/nova_sdk.py
nova_client_sdk-0.1.0.dist-info/LICENSE
nova_client_sdk-0.1.0.dist-info/METADATA
nova_client_sdk-0.1.0.dist-info/WHEEL
nova_client_sdk-0.1.0.dist-info/top_level.txt
nova_client_sdk-0.1.0.dist-info/RECORD
