Metadata-Version: 2.1
Name: nova-client-sdk
Version: 0.1.0
Summary: A Python client SDK for the Nova hackathon
Home-page: https://github.com/ScottyLabs/nova-python-sdk
Author: ScottyLabs
Author-email: hello@scottylabs.org
Classifier: Programming Language :: Python :: 3
Classifier: License :: OSI Approved :: MIT License
Classifier: Operating System :: OS Independent
Requires-Python: >=3.6
License-File: LICENSE
Requires-Dist: requests
